Regression/LogReg.py
Regression/__init__.py
LogReg3-0.1.1.dist-info/LICENSE.txt
LogReg3-0.1.1.dist-info/METADATA
LogReg3-0.1.1.dist-info/WHEEL
LogReg3-0.1.1.dist-info/top_level.txt
LogReg3-0.1.1.dist-info/RECORD
